casqe/__init__.py
casqe/enrichment_engine.py
casqe/myllmservice.py
casqe/prompts.py
casqe/schemes.py
casqe/search_query_enricher.py
casqe/utils.py
casqe-0.0.4.dist-info/METADATA
casqe-0.0.4.dist-info/WHEEL
casqe-0.0.4.dist-info/top_level.txt
casqe-0.0.4.dist-info/RECORD
